Workbook

Sheet indices_macro
A1: Año | B1: ipc (%anual) | C1: deficit (% pib) | D1: deuda (% pib), | E1: balanza com (% pib) | F1: tasa cobertura expo/impo (%) | G1: tasa riesgo pobreza (% pobl) | H1: tasa trabaj activos (% pob) | I1: tasa ocupación (% PEA) | J1: tasa desempleo (% PEA) | K1: interes bonos 10 años (% anual)
A2: 1995 | B2: 4.3 | C2: -6.79 | D2: 61.6 | E2: -2.61 | F2: 86.18 | G2: 19 | H2: =+valores_demogr!E2/valores_demogr!B2*100 -> 42.178563 | I2: =100-J2 -> 77.1 | J2: 22.9 | K2: 11.324
A3: 1996 | B3: 3.2 | C3: -5.87 | D3: 65.4 | E3: -2.25 | F3: 88.47 | G3: 18 | H3: =+valores_demogr!E3/valores_demogr!B3*100 -> 42.239276 | I3: =100-J3 -> 77.9 | J3: 22.1 | K3: 8.622
A4: 1997 | B4: 2 | C4: -3.86 | D4: 64.3 | E4: -2.53 | F4: 87.11 | G4: 20 | H4: =+valores_demogr!E4/valores_demogr!B4*100 -> 42.516277 | I4: =100-J4 -> 79.4 | J4: 20.6 | K4: 6.369
A5: 1998 | B5: 1.4 | C5: -2.63 | D5: 62.4 | E5: -3.96 | F5: 81.93 | G5: 18 | H5: =+valores_demogr!E5/valores_demogr!B5*100 -> 42.903149 | I5: =100-J5 -> 81.4 | J5: 18.6 | K5: 4.795
A6: 1999 | B6: 2.9 | C6: -1.24 | D6: 60.9 | E6: -4.87 | F6: 77.16 | G6: 19 | H6: =+valores_demogr!E6/valores_demogr!B6*100 -> 43.457675 | I6: =100-J6 -> 84.4 | J6: 15.6 | K6: 4.803
A7: 2000 | B7: 4 | C7: -1.16 | D7: 57.8 | E7: -6.84 | F7: 73.81 | G7: 18 | H7: =+valores_demogr!E7/valores_demogr!B7*100 -> 44.428029 | I7: =100-J7 -> 86.1 | J7: 13.9 | K7: 5.509
A8: 2001 | B8: 2.7 | C8: -0.45 | D8: 54.1 | E8: -6.05 | F8: 75.43 | G8: 18 | H8: =+valores_demogr!E8/valores_demogr!B8*100 -> 45.510848 | I8: =100-J8 -> 89.2 | J8: 10.8 | K8: 5.112
A9: 2002 | B9: 4 | C9: -0.31 | D9: 51.2 | E9: -5.56 | F9: 76.13 | G9: 19 | H9: =+valores_demogr!E9/valores_demogr!B9*100 -> 45.812315 | I9: =+valores_demogr!C23/valores_demogr!E23*100 -> 80.753691 | J9: 11.6 | K9: 4.911
A10: 2003 | B10: 2.6 | C10: -0.37 | D10: 47.7 | E10: -5.78 | F10: 74.85 | G10: 19 | H10: =+valores_demogr!E10/valores_demogr!B10*100 -> 45.850922 | I10: =+valores_demogr!C22/valores_demogr!E22*100 -> 79.232642 | J10: 11.4 | K10: 4.129
A11: 2004 | B11: 3.2 | C11: -0.11 | D11: 45.3 | E11: -7.08 | F11: 70.69 | G11: 20.1 | H11: =+valores_demogr!E11/valores_demogr!B11*100 -> 46.398385 | I11: =+valores_demogr!C21/valores_demogr!E21*100 -> 76.980375 | J11: 10.5 | K11: 4.076
A12: 2005 | B12: 3.7 | C12: 1.23 | D12: 42.4 | E12: -8.33 | F12: 66.71 | G12: 20.1 | H12: =+valores_demogr!E12/valores_demogr!B12*100 -> 46.966404 | I12: =+valores_demogr!C20/valores_demogr!E20*100 -> 75.062862 | J12: 8.7 | K12: 3.363
A13: 2006 | B13: 2.7 | C13: 2.12 | D13: 39 | E13: -9.11 | F13: 65.02 | G13: 20.3 | H13: =+valores_demogr!E13/valores_demogr!B13*100 -> 47.474516 | I13: =+valores_demogr!C19/valores_demogr!E19*100 -> 75.846412 | J13: 8.3 | K13: 3.81
A14: 2007 | B14: 4.2 | C14: 1.88 | D14: 35.7 | E14: -9.21 | F14: 65.06 | G14: 19.7 | H14: =+valores_demogr!E14/valores_demogr!B14*100 -> 47.569094 | I14: =+valores_demogr!C18/valores_demogr!E18*100 -> 79.080121 | J14: 8.6 | K14: 4.308
A15: 2008 | B15: 1.4 | C15: -4.56 | D15: 39.6 | E15: -8.51 | F15: 66.89 | G15: 19.8 | H15: =+valores_demogr!E15/valores_demogr!B15*100 -> 47.783842 | I15: =+valores_demogr!C17/valores_demogr!E17*100 -> 81.748262 | J15: 13.8 | K15: 4.396
A16: 2009 | B16: 0.8 | C16: -11.24 | D16: 53.1 | E16: -4.4 | F16: 77.53 | G16: 20.4 | H16: =+valores_demogr!E16/valores_demogr!B16*100 -> 48.247645 | I16: =+valores_demogr!C16/valores_demogr!E16*100 -> 84.224231 | J16: 18.7 | K16: 4.022
A17: 2010 | B17: 3 | C17: -9.49 | D17: 60.3 | E17: -5.08 | F17: 77.8 | G17: 20.7 | H17: =+valores_demogr!E17/valores_demogr!B17*100 -> 48.951752 | I17: =+valores_demogr!C15/valores_demogr!E15*100 -> 90.76891 | J17: 20.1 | K17: 4.335
A18: 2011 | B18: 2.4 | C18: -9.69 | D18: 69.5 | E18: -4.71 | F18: 81.4 | G18: 20.6 | H18: =+valores_demogr!E18/valores_demogr!B18*100 -> 49.030488 | I18: =+valores_demogr!C14/valores_demogr!E14*100 -> 95.3674 | J18: 22.6 | K18: 5.498
A19: 2012 | B19: 2.9 | C19: -11.5 | D19: 89.6 | E19: -3.16 | F19: 87.52 | G19: 20.8 | H19: =+valores_demogr!E19/valores_demogr!B19*100 -> 48.924101 | I19: =+valores_demogr!C13/valores_demogr!E13*100 -> 94.986666 | J19: 25.8 | K19: 5.865
A20: 2013 | B20: 0.3 | C20: -7.49 | D20: 100 | E20: -1.67 | F20: 93.32 | G20: 20.4 | H20: =+valores_demogr!E20/valores_demogr!B20*100 -> 49.079167 | I20: =+valores_demogr!C12/valores_demogr!E12*100 -> 94.384588 | J20: 25.7 | K20: 4.581
A21: 2014 | B21: -1 | C21: -6.04 | D21: 104.4 | E21: -2.49 | F21: 90.43 | G21: 22.2 | H21: =+valores_demogr!E21/valores_demogr!B21*100 -> 49.134368 | I21: =+valores_demogr!C11/valores_demogr!E11*100 -> 92.045817 | J21: 23.7 | K21: 2.738
A22: 2015 | B22: 0 | C22: -5.27 | D22: 102.5 | E22: -2.45 | F22: 90.52 | G22: 22.1 | H22: =+valores_demogr!E22/valores_demogr!B22*100 -> 49.174744 | I22: =+valores_demogr!C10/valores_demogr!E10*100 -> 90.93775 | J22: 20.9 | K22: 1.714
A23: 2016 | B23: 1.6 | C23: -4.22 | D23: 102 | E23: -1.69 | F23: 93.27 | G23: 22.3 | H23: =+valores_demogr!E23/valores_demogr!B23*100 -> 49.259958 | I23: =+valores_demogr!C9/valores_demogr!E9*100 -> 88.673593 | J23: 18.6 | K23: 1.353
A24: 2017 | B24: 1.1 | C24: -3.07 | D24: 101.2 | E24: -2.44 | F24: 90.78 | G24: 21.6 | H24: =+valores_demogr!E24/valores_demogr!B24*100 -> 49.24896 | I24: =+valores_demogr!C8/valores_demogr!E8*100 -> 79.294338 | J24: 16.6 | K24: 1.564
A25: 2018 | B25: 1.2 | C25: -2.55 | D25: 99.8 | E25: -3.07 | F25: 88.78 | G25: 21.5 | H25: =+valores_demogr!E25/valores_demogr!B25*100 -> 49.173084 | I25: =+valores_demogr!C7/valores_demogr!E7*100 -> 71.594463 | J25: 16.6 | K25: 1.44
A26: 2019 | B26: 0.8 | C26: -3.06 | D26: 97.7 | E26: -2.76 | F26: 89.61 | G26: 20.7 | H26: =+valores_demogr!E26/valores_demogr!B26*100 -> 49.178353 | I26: =+valores_demogr!C6/valores_demogr!E6*100 -> 73.33594 | J26: 14.5 | K26: 0.659
A27: 2020 | B27: -0.5 | C27: -9.91 | D27: 119.3 | E27: -1.39 | F27: 94.52 | G27: 21 | H27: =+valores_demogr!E27/valores_demogr!B27*100 -> 49.407689 | I27: =+valores_demogr!C5/valores_demogr!E5*100 -> 68.497746 | J27: 13.8 | K27: 0.401
A28: 2021 | B28: 6.5 | C28: -6.65 | D28: 115.7 | E28: -2.75 | F28: 90.53 | G28: 21.7 | H28: =+valores_demogr!E28/valores_demogr!B28*100 -> 49.446699 | I28: =+valores_demogr!C4/valores_demogr!E4*100 -> 68.771255 | J28: 16.1 | K28: 0.386
A29: 2022 | B29: 5.7 | C29: -4.59 | D29: 109.3 | E29: -5.45 | F29: 84.06 | G29: 20.4 | H29: =+valores_demogr!E29/valores_demogr!B29*100 -> 49.254491 | I29: =+valores_demogr!C3/valores_demogr!E3*100 -> 67.491781 | J29: 13.3 | K29: 2.208
A30: 2023 | B30: 3.1 | C30: -3.34 | D30: 105.2 | E30: -2.92 | F30: 89.99 | G30: 20.2 | H30: =+valores_demogr!E30/valores_demogr!B30*100 -> 49.539184 | I30: =+valores_demogr!C2/valores_demogr!$E2*100 -> 66.218222 | J30: 12.9 | K30: 3.504

Sheet valores_macro
A1: Año | B1: pib (MM € 2023) | C1: pib per capita | D1: pib per PEA | E1: deficit (MM €) | F1: deficit per capita | G1: deficit per PEA | H1: deficit_acum (MM €) | I1: deficit_acum per capita | J1: deficit_acum per PEA | K1: deuda (MM €) | L1: deuda per capita | M1: deuda per PEA | N1: balanza com (MM €) | O1: cant empresas | P1: índice IBEX35 | Q1: indice gini | R1: ipc_acum(%)
A2: 1995 | B2: 889655 | C2: =+B2/(valores_demogr!$B2/1000000) -> 22348.439 | D2: =+B2/(valores_demogr!$E2/1000000) -> 52985.301 | E2: =indices_macro!C30%*valores_macro!B30 -> -50025.217 | F2: =+E2/(valores_demogr!$B2/1000000) -> -1256.6506 | G2: =+E2/(valores_demogr!$E2/1000000) -> -2979.3585 | H2: =+E2 -> -50025.217 | I2: =+H2/(valores_demogr!$B2/1000000) -> -1256.6506 | J2: =+H2/(valores_demogr!$E2/1000000) -> -2979.3585 | K2: =+B2*indices_macro!D2% -> 548027.48 | L2: =+K2/(valores_demogr!$B2/1000000) -> 13766.638 | M2: =+K2/(valores_demogr!$E2/1000000) -> 32638.946 | N2: =+indices_macro!E2%*valores_macro!B2 -> -23219.995 | O2: 2166491 | P2: 3.8 | Q2: 34 | R2: =+(1+indices_macro!B2%) -> 1.043
A3: 1996 | B3: 906141 | C3: =+B3/(valores_demogr!$B3/1000000) -> 22669.774 | D3: =+B3/(valores_demogr!$E3/1000000) -> 53669.893 | E3: =indices_macro!C29%*valores_macro!B29 -> -66751.773 | F3: =+E3/(valores_demogr!$B3/1000000) -> -1669.9913 | G3: =+E3/(valores_demogr!$E3/1000000) -> -3953.6457 | H3: =+H2+E3 -> -116776.99 | I3: =+H3/(valores_demogr!$B3/1000000) -> -2921.5188 | J3: =+H3/(valores_demogr!$E3/1000000) -> -6916.5931 | K3: =+B3*indices_macro!D3% -> 592616.21 | L3: =+K3/(valores_demogr!$B3/1000000) -> 14826.032 | M3: =+K3/(valores_demogr!$E3/1000000) -> 35100.11 | N3: =+indices_macro!E3%*valores_macro!B3 -> -20388.173 | O3: 2242216 | P3: 5.3 | Q3: 34 | R3: =+(1+indices_macro!B3%)*R2 -> 1.076376
A4: 1997 | B4: 931963 | C4: =+B4/(valores_demogr!$B4/1000000) -> 23215.818 | D4: =+B4/(valores_demogr!$E4/1000000) -> 54604.541 | E4: =indices_macro!C28%*valores_macro!B28 -> -92486.804 | F4: =+E4/(valores_demogr!$B4/1000000) -> -2303.9078 | G4: =+E4/(valores_demogr!$E4/1000000) -> -5418.884 | H4: =+H3+E4 -> -209263.79 | I4: =+H4/(valores_demogr!$B4/1000000) -> -5212.9002 | J4: =+H4/(valores_demogr!$E4/1000000) -> -12260.952 | K4: =+B4*indices_macro!D4% -> 599252.21 | L4: =+K4/(valores_demogr!$B4/1000000) -> 14927.771 | M4: =+K4/(valores_demogr!$E4/1000000) -> 35110.72 | N4: =+indices_macro!E4%*valores_macro!B4 -> -23578.664 | O4: 2326296 | P4: 7.6 | Q4: 35 | R4: =+(1+indices_macro!B4%)*R3 -> 1.0979035
A5: 1998 | B5: 978105 | C5: =+B5/(valores_demogr!$B5/1000000) -> 24268.447 | D5: =+B5/(valores_demogr!$E5/1000000) -> 56565.654 | E5: =indices_macro!C27%*valores_macro!B27 -> -125342.27 | F5: =+E5/(valores_demogr!$B5/1000000) -> -3109.9548 | G5: =+E5/(valores_demogr!$E5/1000000) -> -7248.7797 | H5: =+H4+E5 -> -334606.07 | I5: =+H5/(valores_demogr!$B5/1000000) -> -8302.1451 | J5: =+H5/(valores_demogr!$E5/1000000) -> -19350.899 | K5: =+B5*indices_macro!D5% -> 610337.52 | L5: =+K5/(valores_demogr!$B5/1000000) -> 15143.511 | M5: =+K5/(valores_demogr!$E5/1000000) -> 35296.968 | N5: =+indices_macro!E5%*valores_macro!B5 -> -38732.958 | O5: 2422628 | P5: 10.8 | Q5: 34 | R5: =+(1+indices_macro!B5%)*R4 -> 1.1132742
A6: 1999 | B6: 1033501 | C6: =+B6/(valores_demogr!$B6/1000000) -> 25537.345 | D6: =+B6/(valores_demogr!$E6/1000000) -> 58763.717 | E6: =indices_macro!C26%*valores_macro!B26 -> -43313.841 | F6: =+E6/(valores_demogr!$B6/1000000) -> -1070.2655 | G6: =+E6/(valores_demogr!$E6/1000000) -> -2462.7768 | H6: =+H5+E6 -> -377919.91 | I6: =+H6/(valores_demogr!$B6/1000000) -> -9338.231 | J6: =+H6/(valores_demogr!$E6/1000000) -> -21488.106 | K6: =+B6*indices_macro!D6% -> 629402.11 | L6: =+K6/(valores_demogr!$B6/1000000) -> 15552.243 | M6: =+K6/(valores_demogr!$E6/1000000) -> 35787.104 | N6: =+indices_macro!E6%*valores_macro!B6 -> -50331.499 | O6: 2518801 | P6: 11 | Q6: 33 | R6: =+(1+indices_macro!B6%)*R5 -> 1.1455591
A7: 2000 | B7: 1092667 | C7: =+B7/(valores_demogr!$B7/1000000) -> 26869.602 | D7: =+B7/(valores_demogr!$E7/1000000) -> 60478.942 | E7: =indices_macro!C25%*valores_macro!B25 -> -35320.789 | F7: =+E7/(valores_demogr!$B7/1000000) -> -868.56796 | G7: =+E7/(valores_demogr!$E7/1000000) -> -1955 | H7: =+H6+E7 -> -413240.7 | I7: =+H7/(valores_demogr!$B7/1000000) -> -10161.937 | J7: =+H7/(valores_demogr!$E7/1000000) -> -22872.806 | K7: =+B7*indices_macro!D7% -> 631561.53 | L7: =+K7/(valores_demogr!$B7/1000000) -> 15530.63 | M7: =+K7/(valores_demogr!$E7/1000000) -> 34956.829 | N7: =+indices_macro!E7%*valores_macro!B7 -> -74738.423 | O7: 2595392 | P7: 10 | Q7: 32 | R7: =+(1+indices_macro!B7%)*R6 -> 1.1913815
A8: 2001 | B8: 1137262 | C8: =+B8/(valores_demogr!$B8/1000000) -> 27714.256 | D8: =+B8/(valores_demogr!$E8/1000000) -> 60895.933 | E8: =indices_macro!C24%*valores_macro!B24 -> -41492.831 | F8: =+E8/(valores_demogr!$B8/1000000) -> -1011.1504 | G8: =+E8/(valores_demogr!$E8/1000000) -> -2221.7788 | H8: =+H7+E8 -> -454733.53 | I8: =+H8/(valores_demogr!$B8/1000000) -> -11081.529 | J8: =+H8/(valores_demogr!$E8/1000000) -> -24349.202 | K8: =+B8*indices_macro!D8% -> 615258.74 | L8: =+K8/(valores_demogr!$B8/1000000) -> 14993.412 | M8: =+K8/(valores_demogr!$E8/1000000) -> 32944.7 | N8: =+indices_macro!E8%*valores_macro!B8 -> -68804.351 | O8: 2645317 | P8: 8.2 | Q8: 33 | R8: =+(1+indices_macro!B8%)*R7 -> 1.2235488
A9: 2002 | B9: 1184435 | C9: =+B9/(valores_demogr!$B9/1000000) -> 28316.908 | D9: =+B9/(valores_demogr!$E9/1000000) -> 61810.691 | E9: =indices_macro!C23%*valores_macro!B23 -> -55617.701 | F9: =+E9/(valores_demogr!$B9/1000000) -> -1329.6815 | G9: =+E9/(valores_demogr!$E9/1000000) -> -2902.4544 | H9: =+H8+E9 -> -510351.23 | I9: =+H9/(valores_demogr!$B9/1000000) -> -12201.234 | J9: =+H9/(valores_demogr!$E9/1000000) -> -26633.088 | K9: =+B9*indices_macro!D9% -> 606430.72 | L9: =+K9/(valores_demogr!$B9/1000000) -> 14498.257 | M9: =+K9/(valores_demogr!$E9/1000000) -> 31647.074 | N9: =+indices_macro!E9%*valores_macro!B9 -> -65854.586 | O9: 2710400 | P9: 6.1 | Q9: 31 | R9: =+(1+indices_macro!B9%)*R8 -> 1.2724907
A10: 2003 | B10: 1219295 | C10: =+B10/(valores_demogr!$B10/1000000) -> 28657.296 | D10: =+B10/(valores_demogr!$E10/1000000) -> 62501.025 | E10: =indices_macro!C22%*valores_macro!B22 -> -67238.56 | F10: =+E10/(valores_demogr!$B10/1000000) -> -1580.3192 | G10: =+E10/(valores_demogr!$E10/1000000) -> -3446.6466 | H10: =+H9+E10 -> -577589.79 | I10: =+H10/(valores_demogr!$B10/1000000) -> -13575.19 | J10: =+H10/(valores_demogr!$E10/1000000) -> -29607.235 | K10: =+B10*indices_macro!D10% -> 581603.72 | L10: =+K10/(valores_demogr!$B10/1000000) -> 13669.53 | M10: =+K10/(valores_demogr!$E10/1000000) -> 29812.989 | N10: =+indices_macro!E10%*valores_macro!B10 -> -70475.251 | O10: 2813159 | P10: 7.7 | Q10: 31 | R10: =+(1+indices_macro!B10%)*R9 -> 1.3055755
A11: 2004 | B11: 1273344 | C11: =+B11/(valores_demogr!$B11/1000000) -> 29409.972 | D11: =+B11/(valores_demogr!$E11/1000000) -> 63385.767 | E11: =indices_macro!C21%*valores_macro!B21 -> -72912.162 | F11: =+E11/(valores_demogr!$B11/1000000) -> -1684.0262 | G11: =+E11/(valores_demogr!$E11/1000000) -> -3629.4932 | H11: =+H10+E11 -> -650501.95 | I11: =+H11/(valores_demogr!$B11/1000000) -> -15024.411 | J11: =+H11/(valores_demogr!$E11/1000000) -> -32381.325 | K11: =+B11*indices_macro!D11% -> 576824.83 | L11: =+K11/(valores_demogr!$B11/1000000) -> 13322.717 | M11: =+K11/(valores_demogr!$E11/1000000) -> 28713.753 | N11: =+indices_macro!E11%*valores_macro!B11 -> -90152.755 | O11: 2942583 | P11: 9.1 | Q11: 31 | R11: =+(1+indices_macro!B11%)*R10 -> 1.3473539
A12: 2005 | B12: 1331505 | C12: =+B12/(valores_demogr!$B12/1000000) -> 30254.623 | D12: =+B12/(valores_demogr!$E12/1000000) -> 64417.583 | E12: =indices_macro!C20%*valores_macro!B20 -> -89526.472 | F12: =+E12/(valores_demogr!$B12/1000000) -> -2034.2317 | G12: =+E12/(valores_demogr!$E12/1000000) -> -4331.2484 | H12: =+H11+E12 -> -740028.42 | I12: =+H12/(valores_demogr!$B12/1000000) -> -16815.018 | J12: =+H12/(valores_demogr!$E12/1000000) -> -35802.226 | K12: =+B12*indices_macro!D12% -> 564558.12 | L12: =+K12/(valores_demogr!$B12/1000000) -> 12827.96 | M12: =+K12/(valores_demogr!$E12/1000000) -> 27313.055 | N12: =+indices_macro!E12%*valores_macro!B12 -> -110914.37 | O12: 3064129 | P12: 10.7 | Q12: 32.2 | R12: =+(1+indices_macro!B12%)*R11 -> 1.397206
A13: 2006 | B13: 1390319 | C13: =+B13/(valores_demogr!$B13/1000000) -> 31044.537 | D13: =+B13/(valores_demogr!$E13/1000000) -> 65392.003 | E13: =indices_macro!C19%*valores_macro!B19 -> -142865.54 | F13: =+E13/(valores_demogr!$B13/1000000) -> -3190.0552 | G13: =+E13/(valores_demogr!$E13/1000000) -> -6719.5108 | H13: =+H12+E13 -> -882893.96 | I13: =+H13/(valores_demogr!$B13/1000000) -> -19714.205 | J13: =+H13/(valores_demogr!$E13/1000000) -> -41525.869 | K13: =+B13*indices_macro!D13% -> 542224.41 | L13: =+K13/(valores_demogr!$B13/1000000) -> 12107.369 | M13: =+K13/(valores_demogr!$E13/1000000) -> 25502.881 | N13: =+indices_macro!E13%*valores_macro!B13 -> -126658.06 | O13: 3174393 | P13: 14 | Q13: 31.9 | R13: =+(1+indices_macro!B13%)*R12 -> 1.4349306
A14: 2007 | B14: 1451518 | C14: =+B14/(valores_demogr!$B14/1000000) -> 31783.485 | D14: =+B14/(valores_demogr!$E14/1000000) -> 66815.409 | E14: =indices_macro!C18%*valores_macro!B18 -> -127162.94 | F14: =+E14/(valores_demogr!$B14/1000000) -> -2784.4513 | G14: =+E14/(valores_demogr!$E14/1000000) -> -5853.4883 | H14: =+H13+E14 -> -1010056.9 | I14: =+H14/(valores_demogr!$B14/1000000) -> -22116.934 | J14: =+H14/(valores_demogr!$E14/1000000) -> -46494.336 | K14: =+B14*indices_macro!D14% -> 518191.93 | L14: =+K14/(valores_demogr!$B14/1000000) -> 11346.704 | M14: =+K14/(valores_demogr!$E14/1000000) -> 23853.101 | N14: =+indices_macro!E14%*valores_macro!B14 -> -133684.81 | O14: 3336657 | P14: 15.2 | Q14: 31.9 | R14: =+(1+indices_macro!B14%)*R13 -> 1.4951977
A15: 2008 | B15: 1438117 | C15: =+B15/(valores_demogr!$B15/1000000) -> 31101.637 | D15: =+B15/(valores_demogr!$E15/1000000) -> 65088.188 | E15: =indices_macro!C17%*valores_macro!B17 -> -129289.29 | F15: =+E15/(valores_demogr!$B15/1000000) -> -2796.0928 | G15: =+E15/(valores_demogr!$E15/1000000) -> -5851.5446 | H15: =+H14+E15 -> -1139346.2 | I15: =+H15/(valores_demogr!$B15/1000000) -> -24640.228 | J15: =+H15/(valores_demogr!$E15/1000000) -> -51566.026 | K15: =+B15*indices_macro!D15% -> 569494.33 | L15: =+K15/(valores_demogr!$B15/1000000) -> 12316.248 | M15: =+K15/(valores_demogr!$E15/1000000) -> 25774.922 | N15: =+indices_macro!E15%*valores_macro!B15 -> -122383.76 | O15: 3422239 | P15: 9.2 | Q15: 32.4 | R15: =+(1+indices_macro!B15%)*R14 -> 1.5161304
A16: 2009 | B16: 1367976 | C16: =+B16/(valores_demogr!$B16/1000000) -> 29427.306 | D16: =+B16/(valores_demogr!$E16/1000000) -> 60992.211 | E16: =indices_macro!C16%*valores_macro!B16 -> -153760.5 | F16: =+E16/(valores_demogr!$B16/1000000) -> -3307.6291 | G16: =+E16/(valores_demogr!$E16/1000000) -> -6855.5245 | H16: =+H15+E16 -> -1293106.7 | I16: =+H16/(valores_demogr!$B16/1000000) -> -27816.749 | J16: =+H16/(valores_demogr!$E16/1000000) -> -57654.108 | K16: =+B16*indices_macro!D16% -> 726395.26 | L16: =+K16/(valores_demogr!$B16/1000000) -> 15625.899 | M16: =+K16/(valores_demogr!$E16/1000000) -> 32386.864 | N16: =+indices_macro!E16%*valores_macro!B16 -> -60190.944 | O16: 3355830 | P16: 12 | Q16: 32.9 | R16: =+(1+indices_macro!B16%)*R15 -> 1.5282595
A17: 2010 | B17: 1362374 | C17: =+B17/(valores_demogr!$B17/1000000) -> 29193.411 | D17: =+B17/(valores_demogr!$E17/1000000) -> 59637.11 | E17: =indices_macro!C15%*valores_macro!B15 -> -65578.135 | F17: =+E17/(valores_demogr!$B17/1000000) -> -1405.2304 | G17: =+E17/(valores_demogr!$E17/1000000) -> -2870.6438 | H17: =+H16+E17 -> -1358684.8 | I17: =+H17/(valores_demogr!$B17/1000000) -> -29114.358 | J17: =+H17/(valores_demogr!$E17/1000000) -> -59475.619 | K17: =+B17*indices_macro!D17% -> 821511.52 | L17: =+K17/(valores_demogr!$B17/1000000) -> 17603.627 | M17: =+K17/(valores_demogr!$E17/1000000) -> 35961.177 | N17: =+indices_macro!E17%*valores_macro!B17 -> -69208.599 | O17: 3291263 | P17: 9.8 | Q17: 33.5 | R17: =+(1+indices_macro!B17%)*R16 -> 1.5741072
A18: 2011 | B18: 1312311 | C18: =+B18/(valores_demogr!$B18/1000000) -> 28029.923 | D18: =+B18/(valores_demogr!$E18/1000000) -> 57168.354 | E18: =indices_macro!C14%*valores_macro!B14 -> 27288.538 | F18: =+E18/(valores_demogr!$B18/1000000) -> 582.86156 | G18: =+E18/(valores_demogr!$E18/1000000) -> 1188.7737 | H18: =+H17+E18 -> -1331396.3 | I18: =+H18/(valores_demogr!$B18/1000000) -> -28437.57 | J18: =+H18/(valores_demogr!$E18/1000000) -> -57999.769 | K18: =+B18*indices_macro!D18% -> 912056.14 | L18: =+K18/(valores_demogr!$B18/1000000) -> 19480.797 | M18: =+K18/(valores_demogr!$E18/1000000) -> 39732.006 | N18: =+indices_macro!E18%*valores_macro!B18 -> -61809.848 | O18: 3250576 | P18: 8.5 | Q18: 34 | R18: =+(1+indices_macro!B18%)*R17 -> 1.6118858
A19: 2012 | B19: 1242309 | C19: =+B19/(valores_demogr!$B19/1000000) -> 26586.028 | D19: =+B19/(valores_demogr!$E19/1000000) -> 54341.373 | E19: =indices_macro!C13%*valores_macro!B13 -> 29474.763 | F19: =+E19/(valores_demogr!$B19/1000000) -> 630.77453 | G19: =+E19/(valores_demogr!$E19/1000000) -> 1289.292 | H19: =+H18+E19 -> -1301921.5 | I19: =+H19/(valores_demogr!$B19/1000000) -> -27861.766 | J19: =+H19/(valores_demogr!$E19/1000000) -> -56948.958 | K19: =+B19*indices_macro!D19% -> 1113108.9 | L19: =+K19/(valores_demogr!$B19/1000000) -> 23821.081 | M19: =+K19/(valores_demogr!$E19/1000000) -> 48689.87 | N19: =+indices_macro!E19%*valores_macro!B19 -> -39256.964 | O19: 3199617 | P19: 8.1 | Q19: 34.2 | R19: =+(1+indices_macro!B19%)*R18 -> 1.6586305
A20: 2013 | B20: 1195280 | C20: =+B20/(valores_demogr!$B20/1000000) -> 25698.204 | D20: =+B20/(valores_demogr!$E20/1000000) -> 52360.718 | E20: =indices_macro!C12%*valores_macro!B12 -> 16377.512 | F20: =+E20/(valores_demogr!$B20/1000000) -> 352.11217 | G20: =+E20/(valores_demogr!$E20/1000000) -> 717.43714 | H20: =+H19+E20 -> -1285544 | I20: =+H20/(valores_demogr!$B20/1000000) -> -27638.857 | J20: =+H20/(valores_demogr!$E20/1000000) -> -56314.845 | K20: =+B20*indices_macro!D20% -> 1195280 | L20: =+K20/(valores_demogr!$B20/1000000) -> 25698.204 | M20: =+K20/(valores_demogr!$E20/1000000) -> 52360.718 | N20: =+indices_macro!E20%*valores_macro!B20 -> -19961.176 | O20: 3146570 | P20: 9.8 | Q20: 33.7 | R20: =+(1+indices_macro!B20%)*R19 -> 1.6636064
A21: 2014 | B21: 1207155 | C21: =+B21/(valores_demogr!$B21/1000000) -> 25988.51 | D21: =+B21/(valores_demogr!$E21/1000000) -> 52892.734 | E21: =indices_macro!C11%*valores_macro!B11 -> -1400.6784 | F21: =+E21/(valores_demogr!$B21/1000000) -> -30.154823 | G21: =+E21/(valores_demogr!$E21/1000000) -> -61.37216 | H21: =+H20+E21 -> -1286944.7 | I21: =+H21/(valores_demogr!$B21/1000000) -> -27706.281 | J21: =+H21/(valores_demogr!$E21/1000000) -> -56388.801 | K21: =+B21*indices_macro!D21% -> 1260269.8 | L21: =+K21/(valores_demogr!$B21/1000000) -> 27132.005 | M21: =+K21/(valores_demogr!$E21/1000000) -> 55220.014 | N21: =+indices_macro!E21%*valores_macro!B21 -> -30058.16 | O21: 3119310 | P21: 10.2 | Q21: 34.7 | R21: =+(1+indices_macro!B21%)*R20 -> 1.6469703
A22: 2015 | B22: 1275874 | C22: =+B22/(valores_demogr!$B22/1000000) -> 27473.542 | D22: =+B22/(valores_demogr!$E22/1000000) -> 55869.211 | E22: =indices_macro!C10%*valores_macro!B10 -> -4511.3915 | F22: =+E22/(valores_demogr!$B22/1000000) -> -97.144313 | G22: =+E22/(valores_demogr!$E22/1000000) -> -197.5492 | H22: =+H21+E22 -> -1291456.1 | I22: =+H22/(valores_demogr!$B22/1000000) -> -27809.073 | J22: =+H22/(valores_demogr!$E22/1000000) -> -56551.534 | K22: =+B22*indices_macro!D22% -> 1307770.8 | L22: =+K22/(valores_demogr!$B22/1000000) -> 28160.38 | M22: =+K22/(valores_demogr!$E22/1000000) -> 57265.941 | N22: =+indices_macro!E22%*valores_macro!B22 -> -31258.913 | O22: 3186878 | P22: 9.5 | Q22: 34.6 | R22: =+(1+indices_macro!B22%)*R21 -> 1.6469703
A23: 2016 | B23: 1317955 | C23: =+B23/(valores_demogr!$B23/1000000) -> 28326.647 | D23: =+B23/(valores_demogr!$E23/1000000) -> 57504.407 | E23: =indices_macro!C9%*valores_macro!B9 -> -3671.7485 | F23: =+E23/(valores_demogr!$B23/1000000) -> -78.916445 | G23: =+E23/(valores_demogr!$E23/1000000) -> -160.20404 | H23: =+H22+E23 -> -1295127.8 | I23: =+H23/(valores_demogr!$B23/1000000) -> -27836.025 | J23: =+H23/(valores_demogr!$E23/1000000) -> -56508.422 | K23: =+B23*indices_macro!D23% -> 1344314.1 | L23: =+K23/(valores_demogr!$B23/1000000) -> 28893.18 | M23: =+K23/(valores_demogr!$E23/1000000) -> 58654.495 | N23: =+indices_macro!E23%*valores_macro!B23 -> -22273.439 | O23: 3236582 | P23: 9.3 | Q23: 34.5 | R23: =+(1+indices_macro!B23%)*R22 -> 1.6733219
A24: 2017 | B24: 1351558 | C24: =+B24/(valores_demogr!$B24/1000000) -> 28967.059 | D24: =+B24/(valores_demogr!$E24/1000000) -> 58817.606 | E24: =indices_macro!C8%*valores_macro!B8 -> -5117.679 | F24: =+E24/(valores_demogr!$B24/1000000) -> -109.68387 | G24: =+E24/(valores_demogr!$E24/1000000) -> -222.71307 | H24: =+H23+E24 -> -1300245.5 | I24: =+H24/(valores_demogr!$B24/1000000) -> -27867.312 | J24: =+H24/(valores_demogr!$E24/1000000) -> -56584.57 | K24: =+B24*indices_macro!D24% -> 1367776.7 | L24: =+K24/(valores_demogr!$B24/1000000) -> 29314.664 | M24: =+K24/(valores_demogr!$E24/1000000) -> 59523.417 | N24: =+indices_macro!E24%*valores_macro!B24 -> -32978.015 | O24: 3282346 | P24: 10 | Q24: 34.1 | R24: =+(1+indices_macro!B24%)*R23 -> 1.6917284
A25: 2018 | B25: 1385129 | C25: =+B25/(valores_demogr!$B25/1000000) -> 29510.349 | D25: =+B25/(valores_demogr!$E25/1000000) -> 60013.215 | E25: =indices_macro!C7%*valores_macro!B7 -> -12674.937 | F25: =+E25/(valores_demogr!$B25/1000000) -> -270.04114 | G25: =+E25/(valores_demogr!$E25/1000000) -> -549.16454 | H25: =+H24+E25 -> -1312920.4 | I25: =+H25/(valores_demogr!$B25/1000000) -> -27971.936 | J25: =+H25/(valores_demogr!$E25/1000000) -> -56884.649 | K25: =+B25*indices_macro!D25% -> 1382358.7 | L25: =+K25/(valores_demogr!$B25/1000000) -> 29451.328 | M25: =+K25/(valores_demogr!$E25/1000000) -> 59893.188 | N25: =+indices_macro!E25%*valores_macro!B25 -> -42523.46 | O25: 3337646 | P25: 8.7 | Q25: 33.2 | R25: =+(1+indices_macro!B25%)*R24 -> 1.7120291
A26: 2019 | B26: 1415485 | C26: =+B26/(valores_demogr!$B26/1000000) -> 29905.067 | D26: =+B26/(valores_demogr!$E26/1000000) -> 60809.412 | E26: =indices_macro!C6%*valores_macro!B6 -> -12815.412 | F26: =+E26/(valores_demogr!$B26/1000000) -> -270.75226 | G26: =+E26/(valores_demogr!$E26/1000000) -> -550.55171 | H26: =+H25+E26 -> -1325735.9 | I26: =+H26/(valores_demogr!$B26/1000000) -> -28008.93 | J26: =+H26/(valores_demogr!$E26/1000000) -> -56953.777 | K26: =+B26*indices_macro!D26% -> 1382928.8 | L26: =+K26/(valores_demogr!$B26/1000000) -> 29217.251 | M26: =+K26/(valores_demogr!$E26/1000000) -> 59410.795 | N26: =+indices_macro!E26%*valores_macro!B26 -> -39067.386 | O26: 3363197 | P26: 9.6 | Q26: 33 | R26: =+(1+indices_macro!B26%)*R25 -> 1.7257254
A27: 2020 | B27: 1264806 | C27: =+B27/(valores_demogr!$B27/1000000) -> 26684.406 | D27: =+B27/(valores_demogr!$E27/1000000) -> 54008.609 | E27: =indices_macro!C5%*valores_macro!B5 -> -25724.162 | F27: =+E27/(valores_demogr!$B27/1000000) -> -542.71877 | G27: =+E27/(valores_demogr!$E27/1000000) -> -1098.45 | H27: =+H26+E27 -> -1351460 | I27: =+H27/(valores_demogr!$B27/1000000) -> -28512.6 | J27: =+H27/(valores_demogr!$E27/1000000) -> -57708.831 | K27: =+B27*indices_macro!D27% -> 1508913.6 | L27: =+K27/(valores_demogr!$B27/1000000) -> 31834.496 | M27: =+K27/(valores_demogr!$E27/1000000) -> 64432.27 | N27: =+indices_macro!E27%*valores_macro!B27 -> -17580.803 | O27: 3404428 | P27: 8.2 | Q27: 32.1 | R27: =+(1+indices_macro!B27%)*R26 -> 1.7170967
A28: 2021 | B28: 1390779 | C28: =+B28/(valores_demogr!$B28/1000000) -> 29320.982 | D28: =+B28/(valores_demogr!$E28/1000000) -> 59298.158 | E28: =indices_macro!C4%*valores_macro!B4 -> -35973.772 | F28: =+E28/(valores_demogr!$B28/1000000) -> -758.41404 | G28: =+E28/(valores_demogr!$E28/1000000) -> -1533.8011 | H28: =+H27+E28 -> -1387433.8 | I28: =+H28/(valores_demogr!$B28/1000000) -> -29250.457 | J28: =+H28/(valores_demogr!$E28/1000000) -> -59155.53 | K28: =+B28*indices_macro!D28% -> 1609131.3 | L28: =+K28/(valores_demogr!$B28/1000000) -> 33924.376 | M28: =+K28/(valores_demogr!$E28/1000000) -> 68607.969 | N28: =+indices_macro!E28%*valores_macro!B28 -> -38246.423 | O28: 3366570 | P28: 8.7 | Q28: 33 | R28: =+(1+indices_macro!B28%)*R27 -> 1.828708
A29: 2022 | B29: 1454287 | C29: =+B29/(valores_demogr!$B29/1000000) -> 30243.862 | D29: =+B29/(valores_demogr!$E29/1000000) -> 61403.256 | E29: =indices_macro!C3%*valores_macro!B3 -> -53190.477 | F29: =+E29/(valores_demogr!$B29/1000000) -> -1106.1678 | G29: =+E29/(valores_demogr!$E29/1000000) -> -2245.8211 | H29: =+H28+E29 -> -1440624.3 | I29: =+H29/(valores_demogr!$B29/1000000) -> -29959.727 | J29: =+H29/(valores_demogr!$E29/1000000) -> -60826.385 | K29: =+B29*indices_macro!D29% -> 1589535.7 | L29: =+K29/(valores_demogr!$B29/1000000) -> 33056.541 | M29: =+K29/(valores_demogr!$E29/1000000) -> 67113.759 | N29: =+indices_macro!E29%*valores_macro!B29 -> -79258.641 | O29: 3430663 | P29: 8.3 | Q29: 32 | R29: =+(1+indices_macro!B29%)*R28 -> 1.9329444
A30: 2023 | B30: 1497761 | C30: =+B30/(valores_demogr!$B30/1000000) -> 30805.644 | D30: =+B30/(valores_demogr!$E30/1000000) -> 62184.399 | E30: =indices_macro!C2%*valores_macro!B2 -> -60407.575 | F30: =+E30/(valores_demogr!$B30/1000000) -> -1242.4507 | G30: =+E30/(valores_demogr!$E30/1000000) -> -2508.0161 | H30: =+H29+E30 -> -1501031.8 | I30: =+H30/(valores_demogr!$B30/1000000) -> -30872.918 | J30: =+H30/(valores_demogr!$E30/1000000) -> -62320.199 | K30: =+B30*indices_macro!D30% -> 1575644.6 | L30: =+K30/(valores_demogr!$B30/1000000) -> 32407.537 | M30: =+K30/(valores_demogr!$E30/1000000) -> 65417.988 | N30: =+indices_macro!E30%*valores_macro!B30 -> -43734.621 | O30: 3207580 | P30: 10.1 | Q30: 31.5 | R30: =+(1+indices_macro!B30%)*R29 -> 1.9928657

Sheet valores_demogr
A1: Año | B1: total hab | C1: cant ocupados | D1: cant desempleados | E1: cant PEA | F1: cant empleo público | G1: cant empleo privado | H1: cant personas riesgo pobreza
A2: 1995 | B2: 39808374 | C2: 11118437 | D2: 1624110 | E2: 16790600 | F2: 1721000 | G2: 779400 | H2: 8041000
A3: 1996 | B3: 39971329 | C3: 11395042 | D3: 1737578.5 | E3: 16883600 | F3: 1752600 | G3: 967100 | H3: 8154000
A4: 1997 | B4: 40143449 | C4: 11737534 | D4: 2179054.5 | E4: 17067500 | F4: 1790900 | G4: 1362200 | H4: 8711000
A5: 1998 | B5: 40303568 | C5: 11844288 | D5: 1948836 | E5: 17291500 | F5: 1808600 | G5: 1335700 | H5: 8464000
A6: 1999 | B6: 40470182 | C6: 12897885 | D6: 2169171 | E6: 17587400 | F6: 1985700 | G6: 1607600 | H6: 8377000
A7: 2000 | B7: 40665545 | C7: 12934900 | D7: 2509803.8 | E7: 18066900 | F7: 2015800 | G7: 1983900 | H7: 8743000
A8: 2001 | B8: 41035271 | C8: 14808614 | D8: 2945520.6 | E8: 18675500 | F8: 2337200 | G8: 2480600 | H8: 8864000
A9: 2002 | B9: 41827836 | C9: 16991900 | D9: 2232000 | E9: 19162300 | F9: 2672700 | G9: 14319200 | H9: 9328000
A10: 2003 | B10: 42547454 | C10: 17740500 | D10: 2276000 | E10: 19508400 | F10: 2764800 | G10: 14975700 | H10: 9403000
A11: 2004 | B11: 43296335 | C11: 18490900 | D11: 2176000 | E11: 20088800 | F11: 2918600 | G11: 15572300 | H11: 8510000
A12: 2005 | B12: 44009969 | C12: 19509200 | D12: 1860000 | E12: 20669900 | F12: 2916400 | G12: 16592800 | H12: 8670000
A13: 2006 | B13: 44784659 | C13: 20195400 | D13: 1819000 | E13: 21261300 | F13: 2959200 | G13: 17236200 | H13: 8901000
... A30: 2023 | B30: 48619695 | C30: 21389700 | D30: 2831000 | E30: 24085800 | F30: 3576600 | G30: 17813100 | H30: 9567000

Sheet valores_asalariados
A1: Año | B1: salario bruto mediano (€) | C1: umbral riesgo hab (€) | D1: umbral riesgo hogar (€)
A2: 1995 | B2: 19252.126 | C2: 7383.8476 | D2: 15506.08
A3: 1996 | B3: 19412.84 | C3: 7505.6805 | D3: 15761.929
A4: 1997 | B4: 19735.723 | C4: 7685.9778 | D4: 16140.553
A5: 1998 | B5: 20255.446 | C5: 7940.2052 | D5: 16674.431
A6: 1999 | B6: 20869.964 | C6: 8195.1938 | D6: 17209.907
A7: 2000 | B7: 21150.77 | C7: 8352.3186 | D7: 17539.869
A8: 2001 | B8: 21172.836 | C8: 8388.0123 | D8: 17614.826
A9: 2002 | B9: 21429.788 | C9: 8688.8192 | D9: 18246.52
A10: 2003 | B10: 21544.322 | C10: 8886.2924 | D10: 18661.214
A11: 2004 | B11: 21911.852 | C11: 9173.3672 | D11: 19264.663
A12: 2005 | B12: 22119.012 | C12: 8997.9531 | D12: 18895.415
A13: 2006 | B13: 22183.388 | C13: 9245.4995 | D13: 19415.134
... A30: 2023 | B30: 23249 | C30: 10990 | D30: 23078

Sheet indices_sect_privado
A1: Año | C1: riqueza por familia | D1: tasa morosidad bancaria | E1: crédito sector privado
A2: 2023
A3: 2022
A4: 2021
A5: 2020
A6: 2019
A7: 2018
A8: 2017
A9: 2016
A10: 2015
A11: 2014
A12: 2013
A13: 2012
... A30: 1995
